cwru_py3/__init__.py
cwru_py3-0.1.dist-info/LICENSE
cwru_py3-0.1.dist-info/METADATA
cwru_py3-0.1.dist-info/WHEEL
cwru_py3-0.1.dist-info/top_level.txt
cwru_py3-0.1.dist-info/RECORD
