Metadata-Version: 2.1
Name: cwru-py3
Version: 0.1
Summary: Case Western Reserve University Bearing Data
Home-page: https://github.com/94JuHo/cwru_py3
Author: Juho Jung
Author-email: jjs1005k@gmail.com
License: MIT
Keywords: cwru bearing fault diagnosis dataset via python3
Platform: UNKNOWN
Classifier: Development Status :: 3 - Alpha
Classifier: License :: OSI Approved :: MIT License
Classifier: Programming Language :: Python :: 3
Classifier: Programming Language :: Python :: 3.2
Classifier: Programming Language :: Python :: 3.3
Classifier: Programming Language :: Python :: 3.4
Classifier: Programming Language :: Python :: 3.5
Classifier: Programming Language :: Python :: 3.6
Classifier: Programming Language :: Python :: 3.7
Classifier: Topic :: Scientific/Engineering :: Information Analysis
Requires-Dist: numpy
Requires-Dist: scipy
